{
    "posts": [
        {
            "reference": "00001",
            "title": "Title Test",
            "description": "Description Test",
            "main_image": "images/main_image_1_test.jpg",
            "additional_images": [
                "images/additional_image_1_test.jpg",
                "images/additional_image_2_test.jpg",
                "images/additional_image_3_test.jpg"
            ],
            "date_time": 1671017885
        },
        {
            "reference": "00002",
            "title": "Title Test 2",
            "description": "Description Test: 2!",
            "main_image": "images/main_image_2_test.jpg",
            "date_time": 1671017981
        },
        {
            "title": "jsondb",
            "description": "jsondb",
            "date_time": 3232,
            "main_image": "images/main_image-1703834279600-39342288-cat-6463284_640.jpg",
            "reference": "00003"
        },
        {
            "title": "jsondb",
            "description": "jsondb",
            "date_time": 3232,
            "main_image": "images/main_image-1703837188238-558625761-cat-6463284_640.jpg",
            "reference": "00004"
        },
        {
            "title": "jsondb",
            "description": "jsondb",
            "date_time": 3232,
            "main_image": "images/main_image-1703837190595-841041932-cat-6463284_640.jpg",
            "reference": "00005"
        },
        {
            "title": "Test post",
            "description": "Test post description",
            "date_time": 1212121,
            "main_image": "images/main_image-1703838321853-907853161-main_image_test.jpg",
            "reference": "00006"
        },
        {
            "title": "Test post",
            "description": "Test post description",
            "date_time": 1212121,
            "main_image": "images/main_image-1703838348413-327748125-main_image_test.jpg",
            "reference": "00007"
        },
        {
            "title": "Test post",
            "description": "Test post description",
            "date_time": 1212121,
            "main_image": "images/main_image-1703838367635-718002193-main_image_test.jpg",
            "reference": "00008"
        },
        {
            "title": "Test post",
            "description": "Test post description",
            "date_time": 1212121,
            "main_image": "images/main_image-1703838392492-994447181-main_image_test.jpg",
            "reference": "00009"
        },
        {
            "title": "Test post",
            "description": "Test post description",
            "date_time": 1212121,
            "main_image": "images/main_image-1703838525717-688612069-main_image_test.jpg",
            "reference": "00010"
        },
        {
            "title": "Test post",
            "description": "Test post description",
            "date_time": 1212121,
            "main_image": "images/main_image-1703838538503-210069033-main_image_test.jpg",
            "reference": "00011"
        },
        {
            "title": "Test post",
            "description": "Test post description",
            "date_time": 1212121,
            "main_image": "images/main_image-1703838567836-280571142-main_image_test.jpg",
            "reference": "00012"
        },
        {
            "title": "Test post",
            "description": "Test post description",
            "date_time": 1212121,
            "main_image": "images/main_image-1703838582856-320542735-main_image_test.jpg",
            "reference": "00013"
        },
        {
            "title": "Test post",
            "description": "Test post description",
            "date_time": 1212121,
            "main_image": "images/main_image-1703838603631-864022171-main_image_test.jpg",
            "reference": "00014"
        },
        {
            "title": "Test post",
            "description": "Test post description",
            "date_time": 1212121,
            "main_image": "images/main_image-1703838674926-644882037-main_image_test.jpg",
            "reference": "00015"
        },
        {
            "title": "Test post",
            "description": "Test post description",
            "date_time": 1212121,
            "main_image": "images/main_image-1703838692765-499751759-main_image_test.jpg",
            "reference": "00016"
        },
        {
            "title": "Test post",
            "description": "Test post description",
            "date_time": 1212121,
            "main_image": "images/main_image-1703838710711-3690669-main_image_test.jpg",
            "reference": "00017"
        },
        {
            "title": "Test post",
            "description": "Test post description",
            "date_time": 1212121,
            "main_image": "images/main_image-1703838825292-995291749-main_image_test.jpg",
            "reference": "00018"
        },
        {
            "title": "Test post",
            "description": "Test post description",
            "date_time": 1212121,
            "main_image": "images/main_image-1703838922409-787197964-main_image_test.jpg",
            "reference": "00019"
        },
        {
            "title": "Test post",
            "description": "Test post description",
            "date_time": 1212121,
            "main_image": "images/main_image-1703839167796-441957415-main_image_test.jpg",
            "reference": "00020"
        },
        {
            "title": "Test post",
            "description": "Test post description",
            "date_time": 1212121,
            "main_image": "images/main_image-1703839230155-33767529-main_image_test.jpg",
            "reference": "00021"
        },
        {
            "title": "Test post",
            "description": "Test post description",
            "date_time": 1212121,
            "main_image": "images/main_image-1703839434934-51862345-main_image_test.jpg",
            "reference": "00022"
        },
        {
            "title": "Test post",
            "description": "Test post description",
            "date_time": 1212121,
            "main_image": "images/main_image-1703843760729-198536802-main_image_test.jpg",
            "reference": "00023"
        },
        {
            "title": "Test post",
            "description": "Test post description",
            "date_time": 1212121,
            "main_image": "images/main_image-1703843787637-462179894-main_image_test.jpg",
            "reference": "00024"
        },
        {
            "title": "Test post",
            "description": "Test post description",
            "date_time": 1212121,
            "main_image": "images/main_image-1703843841687-521002036-main_image_test.jpg",
            "reference": "00025"
        },
        {
            "title": "Test post",
            "description": "Test post description",
            "date_time": 1212121,
            "main_image": "images/main_image-1703843961388-89799199-main_image_test.jpg",
            "reference": "00026"
        },
        {
            "title": "Test post",
            "description": "Test post description",
            "date_time": 1212121,
            "main_image": "images/main_image-1703844155531-619272048-main_image_test.jpg",
            "reference": "00027"
        },
        {
            "title": "Test post",
            "description": "Test post description",
            "date_time": 1212121,
            "main_image": "images/main_image-1703844191715-507071165-main_image_test.jpg",
            "reference": "00028"
        },
        {
            "title": "jsondba",
            "description": "jsondb",
            "date_time": 21212,
            "main_image": "images/main_image-1703844902851-15130063-cat-2083492_1280.jpg",
            "reference": "00029"
        },
        {
            "title": "Test post",
            "description": "Test post description",
            "date_time": 1212121,
            "main_image": "images/main_image-1703846132530-140267808-main_image_test.jpg",
            "reference": "00030"
        },
        {
            "title": "Test post",
            "description": "Test post description",
            "date_time": 1212121,
            "main_image": "images/main_image-1703846143979-170311896-main_image_test.jpg",
            "reference": "00031"
        },
        {
            "title": "Test post",
            "description": "Test post description",
            "date_time": 1212121,
            "main_image": "images/main_image-1703846188519-187246849-main_image_test.jpg",
            "reference": "00032"
        },
        {
            "title": "Test post",
            "description": "Test post description",
            "date_time": 1212121,
            "main_image": "images/main_image-1703846220560-121331518-main_image_test.jpg",
            "reference": "00033"
        },
        {
            "title": "Test post",
            "description": "Test post description",
            "date_time": 1212121,
            "main_image": "images/main_image-1703846345346-514679215-main_image_test.jpg",
            "reference": "00034"
        },
        {
            "title": "Test post",
            "description": "Test post description",
            "date_time": 1212121,
            "main_image": "images/main_image-1703846357772-296097725-main_image_test.jpg",
            "reference": "00035"
        },
        {
            "title": "Test post",
            "description": "Test post description",
            "date_time": 1212121,
            "main_image": "images/main_image-1703846413054-398831604-main_image_test.jpg",
            "reference": "00036"
        },
        {
            "title": "Test post",
            "description": "Test post description",
            "date_time": 1212121,
            "main_image": "images/main_image-1703846465516-652162459-main_image_test.jpg",
            "reference": "00037"
        },
        {
            "title": "Test post",
            "description": "Test post description",
            "date_time": 1212121,
            "main_image": "images/main_image-1703846561816-267704453-main_image_test.jpg",
            "reference": "00038"
        },
        {
            "title": "Test post",
            "description": "Test post description",
            "date_time": 1212121,
            "main_image": "images/main_image-1703846746645-113481879-main_image_test.jpg",
            "reference": "00039"
        },
        {
            "title": "Test post",
            "description": "Test post description",
            "date_time": 1212121,
            "main_image": "images/main_image-1703846800965-657885068-main_image_test.jpg",
            "reference": "00040"
        },
        {
            "title": "Test post",
            "description": "Test post description",
            "date_time": 1212121,
            "main_image": "images/main_image-1703846837229-82482520-main_image_test.jpg",
            "reference": "00041"
        },
        {
            "title": "Test post",
            "description": "Test post description",
            "date_time": 1212121,
            "main_image": "images/main_image-1703846856446-317600655-main_image_test.jpg",
            "reference": "00042"
        }
    ]
}